invenio_utils/__init__.py
invenio_utils/apache.py
invenio_utils/connector.py
invenio_utils/container.py
invenio_utils/datacite.py
invenio_utils/datastructures.py
invenio_utils/date.py
invenio_utils/deprecation.py
invenio_utils/filedownload.py
invenio_utils/forms.py
invenio_utils/hash.py
invenio_utils/html.py
invenio_utils/htmlwasher.py
invenio_utils/json.py
invenio_utils/mail.py
invenio_utils/memoise.py
invenio_utils/mimetype.py
invenio_utils/orcid.py
invenio_utils/pagination.py
invenio_utils/serializers.py
invenio_utils/shell.py
invenio_utils/text.py
invenio_utils/url.py
invenio_utils/version.py
invenio_utils/viaf.py
invenio_utils/washers.py
invenio_utils/xmlDict.py
invenio_utils/xmlhelpers.py
invenio_utils/autodiscovery/__init__.py
invenio_utils/autodiscovery/checkers.py
invenio_utils/autodiscovery/errors.py
invenio_utils/autodiscovery/helpers.py
invenio_utils/data/__init__.py
invenio_utils/data/latex-to-unicode.kb
invenio_utils/scripts/__init__.py
invenio_utils/translations/invenio.pot
invenio_utils/translations/de/LC_MESSAGES/messages.mo
invenio_utils/translations/de/LC_MESSAGES/messages.po
invenio_utils/translations/es/LC_MESSAGES/messages.mo
invenio_utils/translations/es/LC_MESSAGES/messages.po
invenio_utils/translations/fr/LC_MESSAGES/messages.mo
invenio_utils/translations/fr/LC_MESSAGES/messages.po
invenio_utils/translations/it/LC_MESSAGES/messages.mo
invenio_utils/translations/it/LC_MESSAGES/messages.po
invenio_utils/vcs/__init__.py
invenio_utils/vcs/git.py
invenio_utils/vcs/svn.py
invenio_utils-0.2.0.dist-info/top_level.txt
invenio_utils-0.2.0.dist-info/METADATA
invenio_utils-0.2.0.dist-info/DESCRIPTION.rst
invenio_utils-0.2.0.dist-info/metadata.json
invenio_utils-0.2.0.dist-info/WHEEL
invenio_utils-0.2.0.dist-info/RECORD
